Metadata-Version: 2.1
Name: soapfish2
Version: 0.7.0
Summary: No official SOAP library for Python
Home-page: http://soapfish.org/
Author: Damian Powązka
Author-email: dpowazka@gmail.com
Maintainer: Felix Schwarz
Maintainer-email: felix.schwarz@oss.schwarz.eu
License: BSD-3-Clause
Download-URL: http://soapfish.org/releases/
Keywords: soap,wsdl,xsd,xml,schema,web service
Platform: UNKNOWN
Classifier: Development Status :: 4 - Beta
Classifier: Environment :: Console
Classifier: Environment :: Web Environment
Classifier: Framework :: Django
Classifier: Framework :: Flask
Classifier: Framework :: Pyramid
Classifier: Intended Audience :: Developers
Classifier: License :: OSI Approved :: BSD License
Classifier: Operating System :: OS Independent
Classifier: Programming Language :: Python
Classifier: Programming Language :: Python :: 3
Classifier: Programming Language :: Python :: 3 :: Only
Classifier: Programming Language :: Python :: 3.6
Classifier: Programming Language :: Python :: 3.7
Classifier: Programming Language :: Python :: 3.8
Classifier: Programming Language :: Python :: Implementation :: CPython
Classifier: Topic :: Internet :: WWW/HTTP
Classifier: Topic :: Software Development :: Libraries :: Python Modules
Obsoletes: soapbox
Requires-Python: >=3.6
